acmetk/__init__.py
acmetk/__main__.py
acmetk/database.py
acmetk/main.py
acmetk/plugin_base.py
acmetk/util.py
acmetk/version.py
acmetk/client/__init__.py
acmetk/client/challenge_solver.py
acmetk/client/client.py
acmetk/client/exceptions.py
acmetk/models/__init__.py
acmetk/models/account.py
acmetk/models/authorization.py
acmetk/models/base.py
acmetk/models/certificate.py
acmetk/models/challenge.py
acmetk/models/identifier.py
acmetk/models/messages.py
acmetk/models/order.py
acmetk/plugins/__init__.py
acmetk/plugins/template_solver.py
acmetk/plugins/template_validator.py
acmetk/server/__init__.py
acmetk/server/challenge_validator.py
acmetk/server/external_account_binding.py
acmetk/server/management.py
acmetk/server/pagination.py
acmetk/server/routes.py
acmetk/server/server.py
acmetk-0.0.2.dist-info/LICENSE
acmetk-0.0.2.dist-info/METADATA
acmetk-0.0.2.dist-info/WHEEL
acmetk-0.0.2.dist-info/top_level.txt
acmetk-0.0.2.dist-info/RECORD
